AUTHORS.rst
CHANGELOG.rst
LICENSE
MANIFEST.in
README.rst
setup.py
mama_survey.egg-info/PKG-INFO
mama_survey.egg-info/SOURCES.txt
mama_survey.egg-info/dependency_links.txt
mama_survey.egg-info/not-zip-safe
mama_survey.egg-info/requires.txt
mama_survey.egg-info/top_level.txt
survey/__init__.py
survey/admin.py
survey/constants.py
survey/forms.py
survey/models.py
survey/tests.py
survey/urls.py
survey/views.py
survey/management/__init__.py
survey/management/commands/__init__.py
survey/management/commands/survey_answersheet_csv_export.py
survey/management/commands/survey_holodeck_push.py
survey/migrations/0001_initial.py
survey/migrations/0002_auto__chg_field_multichoiceanswer_answer_sheet__del_unique_multichoice.py
survey/migrations/0003_auto__chg_field_answersheet_questionnaire__del_unique_answersheet_ques.py
survey/migrations/0004_auto__chg_field_multichoiceanswer_question__del_unique_multichoiceansw.py
survey/migrations/0005_auto__chg_field_multichoiceanswer_chosen_option__del_unique_multichoic.py
survey/migrations/0006_auto__chg_field_answersheet_user__del_unique_answersheet_user.py
survey/migrations/0007_auto__add_unique_answersheet_questionnaire_user.py
survey/migrations/0008_auto__add_questionnaireholodeckkeys.py
survey/migrations/0009_auto__add_unique_questionnaireholodeckkeys_questionnaire_metric.py
survey/migrations/0010_auto__del_unique_questionnaireholodeckkeys_metric__del_unique_question.py
survey/migrations/0011_auto__add_eunutritionquiz.py
survey/migrations/0012_auto__add_field_eunutritionquiz_show_on_home_page.py
survey/migrations/0013_auto__add_euquiztopost__del_field_eunutritionquiz_post.py
survey/migrations/0014_auto__del_euquiztopost__del_eunutritionquiz__add_contentquiztopost__ad.py
survey/migrations/0015_auto__add_field_questionnaire_target_survey_users.py
survey/migrations/__init__.py
survey/templates/survey/survey_choice.html
survey/templates/survey/survey_exit.html
survey/templates/survey/survey_form.html
survey/templates/survey/survey_thankyou.html
survey/templates/survey/inclusion_tags/content_quizzes.html
survey/templates/survey/inclusion_tags/survey_listing.html
survey/templatetags/__init__.py
survey/templatetags/survey_inclusion_tags.py